LICENSE
MANIFEST.in
README.md
requirements.txt
setup.py
syspathmodif/__init__.py
syspathmodif/individual_paths.py
syspathmodif/individual_paths_no_type_check.py
syspathmodif/parents.py
syspathmodif/sys_modules.py
syspathmodif/syspathbundle.py
syspathmodif.egg-info/PKG-INFO
syspathmodif.egg-info/SOURCES.txt
syspathmodif.egg-info/dependency_links.txt
syspathmodif.egg-info/requires.txt
syspathmodif.egg-info/top_level.txt
tests/test_suite1_individual_paths.py
tests/test_suite2_syspathbundle.py
tests/test_suite3_sys_modules.py
tests/test_suite4_parent_paths.py