Metadata-Version: 2.4
Name: syspathmodif
Version: 1.6.0
Summary: This library offers concise manners to modify list sys.path. The user should not need to directly interact with that list.
Home-page: https://github.com/GRV96/syspathmodif
Author: Guyllaume Rousseau
License: MIT
Classifier: Development Status :: 5 - Production/Stable
Classifier: Intended Audience :: Developers
Classifier: License :: OSI Approved :: MIT License
Classifier: Operating System :: OS Independent
Classifier: Programming Language :: Python :: 3.10
Classifier: Topic :: Software Development :: Libraries :: Python Modules
Classifier: Topic :: Utilities
License-File: LICENSE
Requires-Dist: strath~=1.0
Dynamic: author
Dynamic: classifier
Dynamic: description
Dynamic: description-content-type
Dynamic: home-page
Dynamic: license
Dynamic: license-file
Dynamic: requires-dist
Dynamic: summary
